{"quote":{"language":"en-US","region":"US","quoteType":"MUTUALFUND","quoteSourceName":"Delayed Quote","triggerable":false,"sourceInterval":15,"exchangeDataDelayedBy":0,"tradeable":false,"exchange":"YHD","exchangeTimezoneName":"America\/New_York","exchangeTimezoneShortName":"EST","gmtOffSetMilliseconds":-18000000,"market":"us_market","esgPopulated":false,"priceHint":2,"regularMarketTime":1561759658,"fullExchangeName":"YHD","marketState":"PREPRE","symbol":"GOLD.NS"},"virtual":{"symbol":"GOLD.NS","name":"GOLD.NS","lastUpdated":1606803664}}